bruteguard/__init__.py
bruteguard/admin.py
bruteguard/apps.py
bruteguard/managers.py
bruteguard/middleware.py
bruteguard/models.py
bruteguard/queues.py
bruteguard/urls.py
bruteguard/validators.py
bruteguard/views.py
bruteguard/migrations/0001_initial.py
bruteguard/migrations/0002_auto_20210927_0558.py
bruteguard/migrations/__init__.py
bruteguard/patterns/__init__.py
bruteguard/patterns/composite.py
bruteguard/patterns/singleton.py
bruteguard/static/css/bruteguard.css
bruteguard/static/js/bruteguard.js
bruteguard/templates/bruteguard/base.html
django_brute_guard-0.1.0.dist-info/AUTHORS.rst
django_brute_guard-0.1.0.dist-info/LICENSE
django_brute_guard-0.1.0.dist-info/METADATA
django_brute_guard-0.1.0.dist-info/WHEEL
django_brute_guard-0.1.0.dist-info/top_level.txt
django_brute_guard-0.1.0.dist-info/RECORD
