Metadata-Version: 2.1
Name: django-brute-guard
Version: 0.1.0
Summary: Django Brute-force guard
Home-page: https://github.com/dcopm999/django-brute-guard
Author: Pavel Tanchev
Author-email: dcopm999@gmail.com
License: MIT
Keywords: django-brute-guard
Platform: UNKNOWN
Classifier: Development Status :: 3 - Alpha
Classifier: Framework :: Django :: 3.2
Classifier: Framework :: Django :: 3.1
Classifier: Framework :: Django :: 3.0
Classifier: Framework :: Django :: 2.2
Classifier: Intended Audience :: Developers
Classifier: License :: OSI Approved :: BSD License
Classifier: Natural Language :: English
Classifier: Programming Language :: Python :: 3
Classifier: Programming Language :: Python :: 3.7
Classifier: Programming Language :: Python :: 3.8
Classifier: Programming Language :: Python :: 3.9
License-File: LICENSE
License-File: AUTHORS.rst
Requires-Dist: django-environ (==0.7.0)
